dbt/adapters/databend/__init__.py
dbt/adapters/databend/__version__.py
dbt/adapters/databend/column.py
dbt/adapters/databend/connections.py
dbt/adapters/databend/impl.py
dbt/adapters/databend/relation.py
dbt/include/databend/__init__.py
dbt/include/databend/dbt_project.yml
dbt/include/databend/profile_template.yml
dbt/include/databend/macros/adapters.sql
dbt/include/databend/macros/catalog.sql
dbt/include/databend/macros/incremental.sql
dbt/include/databend/macros/snapshot.sql
dbt/include/databend/macros/utils.sql
dbt/include/databend/macros/materializations/seed.sql
dbt_databend_native-1.3.0.dist-info/LICENSE
dbt_databend_native-1.3.0.dist-info/METADATA
dbt_databend_native-1.3.0.dist-info/WHEEL
dbt_databend_native-1.3.0.dist-info/top_level.txt
dbt_databend_native-1.3.0.dist-info/RECORD
